Metadata-Version: 2.1
Name: colors-cli
Version: 1.23
Summary: Backlight color for command line interface!
Home-page: UNKNOWN
Author: sobraniebluee
Author-email: dimf29@gmail.com
License: UNKNOWN
Platform: UNKNOWN
